ruian/__init__.py
ruian/api_client.py
ruian/configuration.py
ruian/rest.py
ruian/api/__init__.py
ruian/api/developers_api.py
ruian/api/public_api.py
ruian/models/__init__.py
ruian/models/address.py
ruian/models/administrative_division.py
ruian/models/cadastral_territory.py
ruian/models/coordinates.py
ruian/models/full_address.py
ruian/models/full_cadaster.py
ruian/models/full_settlement.py
ruian/models/jtsk.py
ruian/models/katastralni_uzemi.py
ruian/models/mapovy_list50.py
ruian/models/nearby_address.py
ruian/models/parcela.py
ruian/models/point_jtsk.py
ruian/models/point_wgs.py
ruian/models/polygon_jtsk.py
ruian/models/polygon_wgs.py
ruian/models/povodi.py
ruian/models/settlement.py
ruian/models/wgs.py
ruian/models/zsj.py
test/__init__.py
test/test_address.py
test/test_administrative_division.py
test/test_cadastral_territory.py
test/test_coordinates.py
test/test_developers_api.py
test/test_full_address.py
test/test_full_cadaster.py
test/test_full_settlement.py
test/test_jtsk.py
test/test_katastralni_uzemi.py
test/test_mapovy_list50.py
test/test_nearby_address.py
test/test_parcela.py
test/test_point_jtsk.py
test/test_point_wgs.py
test/test_polygon_jtsk.py
test/test_polygon_wgs.py
test/test_povodi.py
test/test_public_api.py
test/test_settlement.py
test/test_wgs.py
test/test_zsj.py
sysnet_ruian-1.0.0.dist-info/LICENSE
sysnet_ruian-1.0.0.dist-info/METADATA
sysnet_ruian-1.0.0.dist-info/WHEEL
sysnet_ruian-1.0.0.dist-info/top_level.txt
sysnet_ruian-1.0.0.dist-info/RECORD
