Metadata-Version: 2.1
Name: sysnet-ruian
Version: 1.0.0
Summary: SYSNET RÚIAN service REST API
Home-page: 
Author-email: Radim Jaeger <rjaeger@sysnet.cz>
License: Apache License
Project-URL: Homepage, https://github.com/SYSNET-CZ/swagger/tree/main/clients/ruian
Keywords: Swagger,SYSNET RUIAN services API
Classifier: Programming Language :: Python :: 3
Classifier: License :: OSI Approved :: Apache Software License
Classifier: Operating System :: OS Independent
Classifier: Topic :: Internet :: WWW/HTTP :: Dynamic Content
Requires-Python: >=3.4
License-File: LICENSE
Requires-Dist: urllib3 (>=1.15)
Requires-Dist: six (>=1.10)
Requires-Dist: certifi
Requires-Dist: python-dateutil
